[
	{
		"chinese": "手",
		"english": "hand",
		"soundmark": "/hænd/"
	},
	{
		"chinese": "把手",
		"english": "handle",
		"soundmark": "/'hændl/"
	},
	{
		"chinese": "门",
		"english": "door",
		"soundmark": "/dɔr/"
	},
	{
		"chinese": "门把手",
		"english": "door handle",
		"soundmark": "/dɔr/ /'hændl/"
	},
	{
		"chinese": "刀",
		"english": "knife",
		"soundmark": "/naɪf/"
	},
	{
		"chinese": "把手",
		"english": "handle",
		"soundmark": "/'hændl/"
	},
	{
		"chinese": "刀柄",
		"english": "knife handle",
		"soundmark": "/naɪf/ /'hændl/"
	},
	{
		"chinese": "把手",
		"english": "handle",
		"soundmark": "/'hændl/"
	},
	{
		"chinese": "操作",
		"english": "to handle",
		"soundmark": "/tə/ /'hændl/"
	},
	{
		"chinese": "机器",
		"english": "machine",
		"soundmark": "/mə'ʃin/"
	},
	{
		"chinese": "这个",
		"english": "this",
		"soundmark": "/ðɪs/"
	},
	{
		"chinese": "这台机器",
		"english": "this machine",
		"soundmark": "/ðɪs/ /mə'ʃin/"
	},
	{
		"chinese": "操作",
		"english": "to handle",
		"soundmark": "/tə/ /'hændl/"
	},
	{
		"chinese": "操作这台机器",
		"english": "to handle this machine",
		"soundmark": "/tə/ /'hændl/ /ðɪs/ /mə'ʃin/"
	},
	{
		"chinese": "知道",
		"english": "to know",
		"soundmark": "/tə/ /no/"
	},
	{
		"chinese": "我知道",
		"english": "I know",
		"soundmark": "/aɪ/ /no/"
	},
	{
		"chinese": "如何",
		"english": "how",
		"soundmark": "/haʊ/"
	},
	{
		"chinese": "我知道如何操作这台机器",
		"english": "I know how to handle this machine",
		"soundmark": "/aɪ/ /no/ /haʊ/ /tə/ /'hændl/ /ðɪs/ /mə'ʃin/"
	},
	{
		"chinese": "不",
		"english": "don't",
		"soundmark": "/dont/"
	},
	{
		"chinese": "我不知道",
		"english": "I don't know",
		"soundmark": "/aɪ/ /dont/ /no/"
	},
	{
		"chinese": "我不知道如何操作这台机器",
		"english": "I don't know how to handle this machine",
		"soundmark": "/aɪ/ /dont/ /no/ /haʊ/ /tə/ /'hændl/ /ðɪs/ /mə'ʃin/"
	},
	{
		"chinese": "操作这台机器",
		"english": "to handle this machine",
		"soundmark": "/tə/ /'hændl/ /ðɪs/ /mə'ʃin/"
	},
	{
		"chinese": "可以",
		"english": "can",
		"soundmark": "/kæn/"
	},
	{
		"chinese": "我可以操作这台机器",
		"english": "I can handle this machine",
		"soundmark": "/aɪ/ /kæn/ /'hændl/ /ðɪs/ /mə'ʃin/"
	},
	{
		"chinese": "不可以",
		"english": "can't",
		"soundmark": "/kænt/"
	},
	{
		"chinese": "我不可以",
		"english": "I can't",
		"soundmark": "/aɪ/ /kænt/"
	},
	{
		"chinese": "操作这台机器",
		"english": "to handle this machine",
		"soundmark": "/tə/ /'hændl/ /ðɪs/ /mə'ʃin/"
	},
	{
		"chinese": "我不可以操作这台机器",
		"english": "I can't handle this machine",
		"soundmark": "/aɪ/ /kænt/ /'hændl/ /ðɪs/ /mə'ʃin/"
	},
	{
		"chinese": "单独",
		"english": "alone",
		"soundmark": "/ə'lon/"
	},
	{
		"chinese": "我不可以单独操作这台机器",
		"english": "I can't handle this machine alone",
		"soundmark": "/aɪ/ /kænt/ /'hændl/ /ðɪs/ /mə'ʃin/ /ə'lon/"
	},
	{
		"chinese": "我的",
		"english": "my",
		"soundmark": "/maɪ/"
	},
	{
		"chinese": "自己",
		"english": "self",
		"soundmark": "/sɛlf/"
	},
	{
		"chinese": "我自己一个人",
		"english": "myself",
		"soundmark": "/maɪ'sɛlf/"
	},
	{
		"chinese": "通过......的方式",
		"english": "by",
		"soundmark": "/baɪ/"
	},
	{
		"chinese": "通过我自己一个人的方式",
		"english": "by myself",
		"soundmark": "/baɪ/ /maɪ'sɛlf/"
	},
	{
		"chinese": "我不可以操作这台机器",
		"english": "I can't handle this machine",
		"soundmark": "/aɪ/ /kænt/ /'hændl/ /ðɪs/ /mə'ʃin/"
	},
	{
		"chinese": "我不可以一个人操作这台机器",
		"english": "I can't handle this machine by myself",
		"soundmark": "/aɪ/ /kænt/ /'hændl/ /ðɪs/ /mə'ʃin/ /baɪ/ /maɪ'sɛlf/"
	},
	{
		"chinese": "你的",
		"english": "your",
		"soundmark": "/jʊr/"
	},
	{
		"chinese": "自己",
		"english": "self",
		"soundmark": "/sɛlf/"
	},
	{
		"chinese": "你自己一个人",
		"english": "yourself",
		"soundmark": "/jɔr'sɛlf/"
	},
	{
		"chinese": "通过......的方式",
		"english": "by",
		"soundmark": "/baɪ/"
	},
	{
		"chinese": "通过你自己一个人的方式",
		"english": "by yourself",
		"soundmark": "/baɪ/ /jɔr'sɛlf/"
	},
	{
		"chinese": "你",
		"english": "you",
		"soundmark": "/ju/"
	},
	{
		"chinese": "你不可以一个人操作这台机器",
		"english": "you can't handle this machine by yourself",
		"soundmark": "/ju/ /kænt/ /'hændl/ /ðɪs/ /mə'ʃin/ /baɪ/ /jɔr'sɛlf/"
	},
	{
		"chinese": "她自己一个人",
		"english": "herself",
		"soundmark": "/hɝ'sɛlf/"
	},
	{
		"chinese": "她",
		"english": "she",
		"soundmark": "/ʃi/"
	},
	{
		"chinese": "她不可以一个人操作这台机器",
		"english": "she can't handle this machine by herself",
		"soundmark": "/ʃi/ /kænt/ /'hændl/ /ðɪs/ /mə'ʃin/ /baɪ/ /hɝ'sɛlf/"
	},
	{
		"chinese": "操作",
		"english": "to handle",
		"soundmark": "/tə/ /'hændl/"
	},
	{
		"chinese": "操作(ing形式)",
		"english": "handling",
		"soundmark": "/'hændlɪŋ/"
	},
	{
		"chinese": "是；赋值(原型)",
		"english": "be",
		"soundmark": "/bi/"
	},
	{
		"chinese": "正在操作",
		"english": "be handling",
		"soundmark": "/bi/ /'hændlɪŋ/"
	},
	{
		"chinese": "我",
		"english": "I",
		"soundmark": "/aɪ/"
	},
	{
		"chinese": "我(现在)正在操作",
		"english": "I am handling",
		"soundmark": "/aɪ/ /æm/ /'hændlɪŋ/"
	},
	{
		"chinese": "这台机器",
		"english": "this machine",
		"soundmark": "/ðɪs/ /mə'ʃin/"
	},
	{
		"chinese": "我(现在)正在操作这台机器",
		"english": "I am handling this machine",
		"soundmark": "/aɪ/ /æm/ /'hændlɪŋ/ /ðɪs/ /mə'ʃin/"
	},
	{
		"chinese": "问题",
		"english": "problem",
		"soundmark": "/'prɑbləm/"
	},
	{
		"chinese": "这个问题",
		"english": "this problem",
		"soundmark": "/ðɪs/ /'prɑbləm/"
	},
	{
		"chinese": "操作；处理",
		"english": "to handle",
		"soundmark": "/tə/ /'hændl/"
	},
	{
		"chinese": "处理这个问题",
		"english": "to handle this problem",
		"soundmark": "/tə/ /'hændl/ /ðɪs/ /'prɑbləm/"
	},
	{
		"chinese": "知道",
		"english": "to know",
		"soundmark": "/tə/ /no/"
	},
	{
		"chinese": "我知道",
		"english": "I know",
		"soundmark": "/aɪ/ /no/"
	},
	{
		"chinese": "如何",
		"english": "how",
		"soundmark": "/haʊ/"
	},
	{
		"chinese": "我知道如何处理这个问题",
		"english": "I know how to handle this problem",
		"soundmark": "/aɪ/ /no/ /haʊ/ /tə/ /'hændl/ /ðɪs/ /'prɑbləm/"
	},
	{
		"chinese": "不",
		"english": "don't",
		"soundmark": "/dont/"
	},
	{
		"chinese": "我不知道",
		"english": "I don't know",
		"soundmark": "/aɪ/ /dont/ /no/"
	},
	{
		"chinese": "我不知道如何处理这个问题",
		"english": "I don't know how to handle this problem",
		"soundmark": "/aɪ/ /dont/ /no/ /haʊ/ /tə/ /'hændl/ /ðɪs/ /'prɑbləm/"
	},
	{
		"chinese": "自己",
		"english": "self",
		"soundmark": "/sɛlf/"
	},
	{
		"chinese": "我自己一个人",
		"english": "myself",
		"soundmark": "/maɪ'sɛlf/"
	},
	{
		"chinese": "通过......的方式",
		"english": "by",
		"soundmark": "/baɪ/"
	},
	{
		"chinese": "通过我自己一个人的方式",
		"english": "by myself",
		"soundmark": "/baɪ/ /maɪ'sɛlf/"
	},
	{
		"chinese": "我不知道如何处理这个问题",
		"english": "I don't know how to handle this problem",
		"soundmark": "/aɪ/ /dont/ /no/ /haʊ/ /tə/ /'hændl/ /ðɪs/ /'prɑbləm/"
	},
	{
		"chinese": "我不知道如何一个人处理这个问题",
		"english": "I don't know how to handle this problem by myself",
		"soundmark": "/aɪ/ /dont/ /no/ /haʊ/ /tə/ /'hændl/ /ðɪs/ /'prɑbləm/ /baɪ/ /maɪ'sɛlf/"
	},
	{
		"chinese": "操作；处理",
		"english": "to handle",
		"soundmark": "/tə/ /'hændl/"
	},
	{
		"chinese": "处理(ing形式)",
		"english": "handling",
		"soundmark": "/'hændlɪŋ/"
	},
	{
		"chinese": "是；赋值(原型)",
		"english": "be",
		"soundmark": "/bi/"
	},
	{
		"chinese": "正在处理",
		"english": "be handling",
		"soundmark": "/bi/ /'hændlɪŋ/"
	},
	{
		"chinese": "他们",
		"english": "they",
		"soundmark": "/ðe/"
	},
	{
		"chinese": "他们(现在)正在处理",
		"english": "they are handling",
		"soundmark": "/ðe/ /ɚ/ /'hændlɪŋ/"
	},
	{
		"chinese": "那个问题",
		"english": "the problem",
		"soundmark": "/ðə/ /'prɑbləm/"
	},
	{
		"chinese": "他们(现在)正在处理那个问题",
		"english": "they are handling the problem",
		"soundmark": "/ðe/ /ɚ/ /'hændlɪŋ/ /ðə/ /'prɑbləm/"
	},
	{
		"chinese": "警察",
		"english": "the police",
		"soundmark": "/ðə/ /pə'lis/"
	},
	{
		"chinese": "警察(现在)正在处理那个问题",
		"english": "the police are handling the problem",
		"soundmark": "/ðə/ /pə'lis/ /ɚ/ /'hændlɪŋ/ /ðə/ /'prɑbləm/"
	},
	{
		"chinese": "脸",
		"english": "face",
		"soundmark": "/fes/"
	},
	{
		"chinese": "面对",
		"english": "to face",
		"soundmark": "/tə/ /fes/"
	},
	{
		"chinese": "面对(ing形式)",
		"english": "facing",
		"soundmark": "/'fesɪŋ/"
	},
	{
		"chinese": "是；赋值(原型)",
		"english": "be",
		"soundmark": "/bi/"
	},
	{
		"chinese": "正在面对",
		"english": "be facing",
		"soundmark": "/bi/ /'fesɪŋ/"
	},
	{
		"chinese": "他们",
		"english": "they",
		"soundmark": "/ðe/"
	},
	{
		"chinese": "他们(现在)正在面对",
		"english": "they are facing",
		"soundmark": "/ðe/ /ɚ/ /'fesɪŋ/"
	},
	{
		"chinese": "那个问题",
		"english": "the problem",
		"soundmark": "/ðə/ /'prɑbləm/"
	},
	{
		"chinese": "他们(现在)正在面对的那个问题",
		"english": "the problem they are facing",
		"soundmark": "/ðə/ /'prɑbləm/ /ðe/ /ɚ/ /'fesɪŋ/"
	},
	{
		"chinese": "警察(现在)正在处理那个问题",
		"english": "the police are handling the problem",
		"soundmark": "/ðə/ /pə'lis/ /ɚ/ /'hændlɪŋ/ /ðə/ /'prɑbləm/"
	},
	{
		"chinese": "警察(现在)正在处理他们(现在)正在面对的那个问题",
		"english": "the police are handling the problem they are facing",
		"soundmark": "/ðə/ /pə'lis/ /ɚ/ /'hændlɪŋ/ /ðə/ /'prɑbləm/ /ðe/ /ɚ/ /'fesɪŋ/"
	},
	{
		"chinese": "挑战",
		"english": "challenge",
		"soundmark": "/'tʃælɪndʒ/"
	},
	{
		"chinese": "挑战(复数)",
		"english": "challenges",
		"soundmark": "/ˈtʃælɪndʒɪz/"
	},
	{
		"chinese": "操作；处理；应对",
		"english": "to handle",
		"soundmark": "/tə/ /'hændl/"
	},
	{
		"chinese": "应对挑战",
		"english": "to handle challenges",
		"soundmark": "/tə/ /'hændl/ /ˈtʃælɪndʒɪz/"
	},
	{
		"chinese": "生活",
		"english": "life",
		"soundmark": "/laɪf/"
	},
	{
		"chinese": "生活的",
		"english": "life's",
		"soundmark": "/laɪfs/"
	},
	{
		"chinese": "生活的挑战",
		"english": "life's challenges",
		"soundmark": "/laɪfs/ /ˈtʃælɪndʒɪz/"
	},
	{
		"chinese": "操作；处理；应对",
		"english": "to handle",
		"soundmark": "/tə/ /'hændl/"
	},
	{
		"chinese": "应对生活的挑战",
		"english": "to handle life's challenges",
		"soundmark": "/tə/ /'hændl/ /laɪfs/ /ˈtʃælɪndʒɪz/"
	},
	{
		"chinese": "知道",
		"english": "to know",
		"soundmark": "/tə/ /no/"
	},
	{
		"chinese": "我知道",
		"english": "I know",
		"soundmark": "/aɪ/ /no/"
	},
	{
		"chinese": "我不知道",
		"english": "I don't know",
		"soundmark": "/aɪ/ /dont/ /no/"
	},
	{
		"chinese": "如何",
		"english": "how",
		"soundmark": "/haʊ/"
	},
	{
		"chinese": "我不知道如何应对生活的挑战",
		"english": "I don't know how to handle life's challenges",
		"soundmark": "/aɪ/ /dont/ /no/ /haʊ/ /tə/ /'hændl/ /laɪfs/ /ˈtʃælɪndʒɪz/"
	},
	{
		"chinese": "我自己一个人",
		"english": "by myself",
		"soundmark": "/baɪ/ /maɪ'sɛlf/"
	},
	{
		"chinese": "我不知道如何一个人应对生活的挑战",
		"english": "I don't know how to handle life's challenges by myself",
		"soundmark": "/aɪ/ /dont/ /no/ /haʊ/ /tə/ /'hændl/ /laɪfs/ /ˈtʃælɪndʒɪz/ /baɪ/ /maɪ'sɛlf/"
	},
	{
		"chinese": "力量",
		"english": "force",
		"soundmark": "/fɔrs/"
	},
	{
		"chinese": "强迫",
		"english": "to force",
		"soundmark": "/tə/ /fɔrs/"
	},
	{
		"chinese": "你的",
		"english": "your",
		"soundmark": "/jʊr/"
	},
	{
		"chinese": "自己",
		"english": "self",
		"soundmark": "/sɛlf/"
	},
	{
		"chinese": "你自己",
		"english": "yourself",
		"soundmark": "/jɔr'sɛlf/"
	},
	{
		"chinese": "强迫你自己",
		"english": "to force yourself",
		"soundmark": "/tə/ /fɔrs/ /jɔr'sɛlf/"
	},
	{
		"chinese": "需要",
		"english": "need",
		"soundmark": "/nid/"
	},
	{
		"chinese": "你需要",
		"english": "you need",
		"soundmark": "/ju/ /nid/"
	},
	{
		"chinese": "不",
		"english": "don't",
		"soundmark": "/dont/"
	},
	{
		"chinese": "你不需要",
		"english": "you don't need",
		"soundmark": "/ju/ /dont/ /nid/"
	},
	{
		"chinese": "你不需要强迫你自己",
		"english": "you don't need to force yourself",
		"soundmark": "/ju/ /dont/ /nid/ /tə/ /fɔrs/ /jɔr'sɛlf/"
	},
	{
		"chinese": "生活",
		"english": "life",
		"soundmark": "/laɪf/"
	},
	{
		"chinese": "挑战(复数)",
		"english": "challenges",
		"soundmark": "/ˈtʃælɪndʒɪz/"
	},
	{
		"chinese": "生活的挑战",
		"english": "life's challenges",
		"soundmark": "/laɪfs/ /ˈtʃælɪndʒɪz/"
	},
	{
		"chinese": "操作；处理；应对",
		"english": "to handle",
		"soundmark": "/tə/ /'hændl/"
	},
	{
		"chinese": "应对生活的挑战",
		"english": "to handle life's challenges",
		"soundmark": "/tə/ /'hændl/ /laɪfs/ /ˈtʃælɪndʒɪz/"
	},
	{
		"chinese": "独自",
		"english": "alone",
		"soundmark": "/ə'lon/"
	},
	{
		"chinese": "独自应对生活的挑战",
		"english": "to handle life's challenges alone",
		"soundmark": "/tə/ /'hændl/ /laɪfs/ /ˈtʃælɪndʒɪz/ /ə'lon/"
	},
	{
		"chinese": "你不需要强迫你自己",
		"english": "you don't need to force yourself",
		"soundmark": "/ju/ /dont/ /nid/ /tə/ /fɔrs/ /jɔr'sɛlf/"
	},
	{
		"chinese": "你不需要强迫你自己独自应对生活的挑战",
		"english": "you don't need to force yourself to handle life's challenges alone",
		"soundmark": "/ju/ /dont/ /nid/ /tə/ /fɔrs/ /jɔr'sɛlf/ /tə/ /'hændl/ /laɪfs/ /ˈtʃælɪndʒɪz/ /ə'lon/"
	}
]
